napari_labels/__init__.py
napari_labels/_widget.py
napari_labels/napari.yaml
napari_labels-0.0.4.dist-info/licenses/LICENSE
napari_labels-0.0.4.dist-info/METADATA
napari_labels-0.0.4.dist-info/WHEEL
napari_labels-0.0.4.dist-info/entry_points.txt
napari_labels-0.0.4.dist-info/top_level.txt
napari_labels-0.0.4.dist-info/RECORD
